riscv_ctg/__init__.py
riscv_ctg/constants.py
riscv_ctg/cross_comb.py
riscv_ctg/csr_comb.py
riscv_ctg/ctg.py
riscv_ctg/dsp_function.py
riscv_ctg/function_generators.py
riscv_ctg/generator.py
riscv_ctg/helpers.py
riscv_ctg/log.py
riscv_ctg/main.py
riscv_ctg/requirements.txt
riscv_ctg/utils.py
riscv_ctg/data/fd.yaml
riscv_ctg/data/imc.yaml
riscv_ctg/data/template.yaml
riscv_ctg/env/arch_test.h
riscv_ctg/env/encoding.h
tests/__init__.py
tests/test_riscv_ctg.py
riscv_ctg-0.12.2.dist-info/LICENSE.incore
riscv_ctg-0.12.2.dist-info/METADATA
riscv_ctg-0.12.2.dist-info/WHEEL
riscv_ctg-0.12.2.dist-info/entry_points.txt
riscv_ctg-0.12.2.dist-info/top_level.txt
riscv_ctg-0.12.2.dist-info/RECORD
