Metadata-Version: 2.1
Name: riscv-ctg
Version: 0.12.2
Summary: RISC-V CTG
Home-page: https://github.com/riscv/riscv-ctg
Author: InCore Semiconductors Pvt. Ltd.
Author-email: info@incoresemi.com
License: BSD-3-Clause
Keywords: riscv_ctg
Platform: UNKNOWN
Classifier: Programming Language :: Python :: 3.6
Classifier: License :: OSI Approved :: BSD License
Classifier: Development Status :: 4 - Beta
Requires-Python: >=3.6.0
Requires-Dist: click
Requires-Dist: ruamel.yaml >=0.16.0
Requires-Dist: colorlog
Requires-Dist: python-constraint
Requires-Dist: riscv-isac >=0.14.0
